LICENSE
MANIFEST.in
README.md
setup.cfg
setup.py
cite_tools/__init__.py
cite_tools/utils.py
cite_tools.egg-info/PKG-INFO
cite_tools.egg-info/SOURCES.txt
cite_tools.egg-info/dependency_links.txt
cite_tools.egg-info/not-zip-safe
cite_tools.egg-info/requires.txt
cite_tools.egg-info/top_level.txt