Metadata-Version: 2.1
Name: cite-tools
Version: 0.1a1
Summary: Python library for the CITE architecture
Home-page: http://github.com/scaife-viewer/cite-tools/
Author: Scaife Viewer Team
Author-email: jtauber+scaife@jtauber.com
License: MIT
Platform: UNKNOWN
Classifier: Development Status :: 3 - Alpha
Classifier: Intended Audience :: Developers
Classifier: License :: OSI Approved :: MIT License
Classifier: Operating System :: OS Independent
Classifier: Programming Language :: Python
Classifier: Programming Language :: Python :: 3
Classifier: Topic :: Software Development :: Libraries :: Python Modules
Provides-Extra: dev
